openbb_famafrench/__init__.py
openbb_famafrench/famafrench_router.py
openbb_famafrench/models/__init__.py
openbb_famafrench/models/breakpoints.py
openbb_famafrench/models/country_portfolio_returns.py
openbb_famafrench/models/factors.py
openbb_famafrench/models/international_index_returns.py
openbb_famafrench/models/regional_portfolio_returns.py
openbb_famafrench/models/us_portfolio_returns.py
openbb_famafrench/py.typed
openbb_famafrench/utils/__init__.py
openbb_famafrench/utils/constants.py
openbb_famafrench/utils/helpers.py
openbb_famafrench-1.1.1.dist-info/METADATA
openbb_famafrench-1.1.1.dist-info/WHEEL
openbb_famafrench-1.1.1.dist-info/entry_points.txt
openbb_famafrench-1.1.1.dist-info/RECORD
